appliapps/__init__.py
appliapps/appliapps.py
appliapps/cli.py
appliapps/examples/__init__.py
appliapps/examples/echobasic.py
appliapps/examples/meta2.py
appliapps/examples/metabasic.py
appliapps-0.1.3.dist-info/AUTHORS.rst
appliapps-0.1.3.dist-info/LICENSE
appliapps-0.1.3.dist-info/METADATA
appliapps-0.1.3.dist-info/WHEEL
appliapps-0.1.3.dist-info/entry_points.txt
appliapps-0.1.3.dist-info/top_level.txt
appliapps-0.1.3.dist-info/RECORD
