Metadata-Version: 2.1
Name: appliapps
Version: 0.1.3
Summary: Applicake nodes
Home-page: https://github.com/malmstroem/appliapps
Author: Lars Malmstroem
Author-email: lars@malmstroem.net
License: BSD license
Keywords: appliapps
Platform: UNKNOWN
Classifier: Development Status :: 2 - Pre-Alpha
Classifier: Intended Audience :: Developers
Classifier: License :: OSI Approved :: BSD License
Classifier: Natural Language :: English
Classifier: Programming Language :: Python :: 2
Classifier: Programming Language :: Python :: 2.7
Classifier: Programming Language :: Python :: 3
Classifier: Programming Language :: Python :: 3.4
Classifier: Programming Language :: Python :: 3.5
Classifier: Programming Language :: Python :: 3.6
Classifier: Programming Language :: Python :: 3.7
Requires-Dist: Click (>=6.0)
Requires-Dist: applicake
